Flask_AuditLog/__init__.py
Flask_AuditLog-1.0.dist-info/LICENSE
Flask_AuditLog-1.0.dist-info/METADATA
Flask_AuditLog-1.0.dist-info/WHEEL
Flask_AuditLog-1.0.dist-info/top_level.txt
Flask_AuditLog-1.0.dist-info/RECORD
