Metadata-Version: 2.1
Name: Flask-AuditLog
Version: 1.0
Summary: Request logging for Flask
Home-page: https://github.com/vwt-digital/flask-auditlog
Author: VolkerWessels Telecom
Author-email: opensource@vwt.digital
License: UNKNOWN
Platform: UNKNOWN
Classifier: Programming Language :: Python :: 3
Classifier: License :: OSI Approved :: GNU General Public License v3 (GPLv3)
Classifier: Operating System :: OS Independent
Requires-Python: >=3.6
